AnimeScraper/AsyncScraper.py
AnimeScraper/SyncScraper.py
AnimeScraper/__init__.py
AnimeScraper/_cache_utils.py
AnimeScraper/_model.py
AnimeScraper/_parse_anime_data.py
AnimeScraper/animescraper_server.py
AnimeScraper/async_malscraper.py
AnimeScraper/cli.py
AnimeScraper/exceptions.py
AnimeScraper/sync_malscraper.py
animescraper-1.1.8.dist-info/LICENSE.md
animescraper-1.1.8.dist-info/METADATA
animescraper-1.1.8.dist-info/WHEEL
animescraper-1.1.8.dist-info/entry_points.txt
animescraper-1.1.8.dist-info/RECORD
