Metadata-Version: 2.1
Name: AnimeScraper
Version: 1.1.8
Summary: A Simple library to get Anime and Character information. It scrapes all information from Myanimelist website.
Home-page: https://github.com/togashigreat/AnimeScraper
License: GPL-V3.0
Keywords: anime,anime scraper,myanimelist,anime cli,manga,anime library,anime api,python anime,fastapi
Author: Muhammad MuQiT
Requires-Python: >=3.10,<4.0
Classifier: Development Status :: 5 - Production/Stable
Classifier: Intended Audience :: Developers
Classifier: License :: OSI Approved :: GNU General Public License v3 (GPLv3)
Classifier: License :: Other/Proprietary License
Classifier: Programming Language :: Python :: 3
Classifier: Programming Language :: Python :: 3.10
Classifier: Programming Language :: Python :: 3.11
Classifier: Programming Language :: Python :: 3.12
Classifier: Programming Language :: Python :: 3.13
Classifier: Topic :: Internet :: WWW/HTTP :: Dynamic Content
Classifier: Topic :: Software Development :: Libraries :: Python Modules
Requires-Dist: aiohttp (>=3.11.6,<4.0.0)
Requires-Dist: aiolimiter (>=1.2.0,<2.0.0)
Requires-Dist: aiosqlite (>=0.20.0,<0.21.0)
Requires-Dist: beautifulsoup4 (>=4.12.1,<5.0.0)
Requires-Dist: click (>=8.1.7,<9.0.0)
Requires-Dist: fastapi (>=0.115.4)
Requires-Dist: httpx (>=0.28.0,<0.29.0)
Requires-Dist: rapidfuzz (>=3.9.6,<4.0.0)
Requires-Dist: uvicorn (>=0.32.0)
Project-URL: Repository, https://github.com/togashigreat/AnimeScraper
